Metadata-Version: 2.1
Name: oneNeuron-pypi-ndangol4873
Version: 0.0.3
Summary: Its an implementation of perceptron
Home-page: https://github.com/ndangol4873/oneNeuron_pypi 
Author: ndangol4873
Author-email: nareshkadambi@gmail.com
License: UNKNOWN
Project-URL: Bug Tracker, https://github.com/{USERNAME}/{PROJECT_NAME}/issues
Platform: UNKNOWN
Classifier: Programming Language :: Python :: 3
Classifier: License :: OSI Approved :: MIT License
Classifier: Operating System :: OS Independent
Requires-Python: >=3.7
License-File: LICENSE
Requires-Dist: numpy
Requires-Dist: tqdm
